{
    "rows":[
        {
            "label":"F",
            "address":"0x20",
            "output":[-1,8,7,6,5,4,3,2,1,0]
        },
        {
            "label":"E",
            "address":"0x21",
            "output":[-1,8,7,6,5,4,3,2,1,0]
        },
        {
            "label":"D",
            "address":"0x22",
            "output":[-1,8,7,6,5,4,3,2,1,0]
        },
        {
            "label":"C",
            "address":"0x23",
            "output":[-1,8,7,6,5,4,3,2,1,0]
        },
        {
            "label":"B",
            "address":"0x24",
            "output":[-1,8,7,6,5,4,3,2,1,0]
        },
        {
            "label":"A",
            "address":"0x25",
            "output":[-1,8,7,6,5,4,3,2,1,0]
        }
    ],
    "row_status":[
        {
            "address":"0x20",
            "output":15
        },
        {
            "address":"0x21",
            "output":15
        },
        {
            "address":"0x22",
            "output":15
        },
        {
            "address":"0x23",
            "output":15
        },
        {
            "address":"0x24",
            "output":15
        },
        {
            "address":"0x25",
            "output":15
        }
    ],
    "compressor":{
        "tstat_bypass":{
            "address":"0x20",
            "output":9,
            "invert":true
        },
        "control":{
            "address":"0x20",
            "output":10,
            "invert":true
        }
    },
    "aux_relays":[
        {
            "address":"0x20",
            "output":11,
            "invert":true
        },
        {
            "address":"0x20",
            "output":12,
            "invert":true
        }
    ],
    "keypad":{
        "output":[21,20,26],
        "input":[5,6,12,13,19,20]
    },
    "display":{
        "sclk":11,
        "mosi":10,
        "cs":8,
        "dc":{
            "output":24
        },
        "rst":{
            "output":25
        }
    },
    "door":{
        "input":14
    },
    "vend_confirm":{
        "input":7
    },
    "climate":{
        "type":"2302",
        "input":4
    }
}